<?xml version="1.0" encoding="utf-8" ?>
<Patch>

  <!-- #region MJobs_Rescuing -->

  <Operation Class="ManyJobs.PatchOps.IfWorkTypeIsEnabled">
    <workType>MJobs_Rescuing</workType>
    <operations>

      <li Class="PatchOperationAdd">
        <xpath>/Defs/ThingDef[defName="RPP_Bot_ER_I" or defName="RPP_Bot_ER_II" or defName="RPP_Bot_ER_III" or defName="RPP_Bot_ER_IV" or defName="RPP_Bot_ER_V"]/robotWorkTypes</xpath>
        <value>
          <li>
            <workTypeDef>MJobs_Rescuing</workTypeDef>
            <priority>1</priority>
          </li>
        </value>
      </li>

      <li Class="PatchOperationAdd">
        <xpath>/Defs/ThingDef[defName="RPP_Bot_ER_I" or defName="RPP_Bot_ER_II" or defName="RPP_Bot_ER_III" or defName="RPP_Bot_ER_IV" or defName="RPP_Bot_ER_V"]/race/mechEnabledWorkTypes</xpath>
        <value>
          <li>MJobs_Rescuing</li>
        </value>
      </li>

      <li Class="PatchOperationAdd">
        <xpath>/Defs/ThingDef[defName="RPP_Bot_ER_I" or defName="RPP_Bot_ER_II" or defName="RPP_Bot_ER_III" or defName="RPP_Bot_ER_IV" or defName="RPP_Bot_ER_V"]/race/mechWorkTypePriorities</xpath>
        <value>
          <MJobs_Rescuing>1</MJobs_Rescuing>
        </value>
      </li>

      <li Class="PatchOperationAdd">
        <xpath>/Defs/ThingDef[defName="RPP_Bot_Omni_I" or defName="RPP_Bot_Omni_II" or defName="RPP_Bot_Omni_III" or defName="RPP_Bot_Omni_IV" or defName="RPP_Bot_Omni_V"]/robotWorkTypes</xpath>
        <value>
          <li>
            <workTypeDef>MJobs_Rescuing</workTypeDef>
            <priority>1</priority>
          </li>
        </value>
      </li>

      <li Class="PatchOperationAdd">
        <xpath>/Defs/ThingDef[defName="RPP_Bot_Omni_I" or defName="RPP_Bot_Omni_II" or defName="RPP_Bot_Omni_III" or defName="RPP_Bot_Omni_IV" or defName="RPP_Bot_Omni_V"]/race/mechEnabledWorkTypes</xpath>
        <value>
          <li>MJobs_Rescuing</li>
        </value>
      </li>

      <li Class="PatchOperationAdd">
        <xpath>/Defs/ThingDef[defName="RPP_Bot_Omni_I" or defName="RPP_Bot_Omni_II" or defName="RPP_Bot_Omni_III" or defName="RPP_Bot_Omni_IV" or defName="RPP_Bot_Omni_V"]/race/mechWorkTypePriorities</xpath>
        <value>
          <MJobs_Rescuing>1</MJobs_Rescuing>
        </value>
      </li>

    </operations>
  </Operation>

  <!-- #endregion -->

  <!-- #region MJobs_Operating -->

  <Operation Class="ManyJobs.PatchOps.IfWorkTypeIsEnabled">
    <workType>MJobs_Operating</workType>
    <operations>

      <li Class="PatchOperationAdd">
        <xpath>/Defs/ThingDef[defName="RPP_Bot_ER_I" or defName="RPP_Bot_ER_II" or defName="RPP_Bot_ER_III" or defName="RPP_Bot_ER_IV" or defName="RPP_Bot_ER_V"]/robotWorkTypes</xpath>
        <value>
          <li>
            <workTypeDef>MJobs_Operating</workTypeDef>
            <priority>1</priority>
          </li>
        </value>
      </li>

      <li Class="PatchOperationAdd">
        <xpath>/Defs/ThingDef[defName="RPP_Bot_ER_I" or defName="RPP_Bot_ER_II" or defName="RPP_Bot_ER_III" or defName="RPP_Bot_ER_IV" or defName="RPP_Bot_ER_V"]/race/mechEnabledWorkTypes</xpath>
        <value>
          <li>MJobs_Operating</li>
        </value>
      </li>

      <li Class="PatchOperationAdd">
        <xpath>/Defs/ThingDef[defName="RPP_Bot_ER_I" or defName="RPP_Bot_ER_II" or defName="RPP_Bot_ER_III" or defName="RPP_Bot_ER_IV" or defName="RPP_Bot_ER_V"]/race/mechWorkTypePriorities</xpath>
        <value>
          <MJobs_Operating>1</MJobs_Operating>
        </value>
      </li>

      <li Class="PatchOperationAdd">
        <xpath>/Defs/ThingDef[defName="RPP_Bot_Omni_I" or defName="RPP_Bot_Omni_II" or defName="RPP_Bot_Omni_III" or defName="RPP_Bot_Omni_IV" or defName="RPP_Bot_Omni_V"]/robotWorkTypes</xpath>
        <value>
          <li>
            <workTypeDef>MJobs_Operating</workTypeDef>
            <priority>1</priority>
          </li>
        </value>
      </li>

      <li Class="PatchOperationAdd">
        <xpath>/Defs/ThingDef[defName="RPP_Bot_Omni_I" or defName="RPP_Bot_Omni_II" or defName="RPP_Bot_Omni_III" or defName="RPP_Bot_Omni_IV" or defName="RPP_Bot_Omni_V"]/race/mechEnabledWorkTypes</xpath>
        <value>
          <li>MJobs_Operating</li>
        </value>
      </li>

      <li Class="PatchOperationAdd">
        <xpath>/Defs/ThingDef[defName="RPP_Bot_Omni_I" or defName="RPP_Bot_Omni_II" or defName="RPP_Bot_Omni_III" or defName="RPP_Bot_Omni_IV" or defName="RPP_Bot_Omni_V"]/race/mechWorkTypePriorities</xpath>
        <value>
          <MJobs_Operating>1</MJobs_Operating>
        </value>
      </li>

    </operations>
  </Operation>

  <!-- #endregion -->

  <!-- #region MJobs_Caring -->

  <Operation Class="ManyJobs.PatchOps.IfWorkTypeIsEnabled">
    <workType>MJobs_Caring</workType>
    <operations>

      <li Class="PatchOperationAdd">
        <xpath>/Defs/ThingDef[defName="RPP_Bot_ER_I" or defName="RPP_Bot_ER_II" or defName="RPP_Bot_ER_III" or defName="RPP_Bot_ER_IV" or defName="RPP_Bot_ER_V"]/robotWorkTypes</xpath>
        <value>
          <li>
            <workTypeDef>MJobs_Caring</workTypeDef>
            <priority>1</priority>
          </li>
        </value>
      </li>

      <li Class="PatchOperationAdd">
        <xpath>/Defs/ThingDef[defName="RPP_Bot_ER_I" or defName="RPP_Bot_ER_II" or defName="RPP_Bot_ER_III" or defName="RPP_Bot_ER_IV" or defName="RPP_Bot_ER_V"]/race/mechEnabledWorkTypes</xpath>
        <value>
          <li>MJobs_Caring</li>
        </value>
      </li>

      <li Class="PatchOperationAdd">
        <xpath>/Defs/ThingDef[defName="RPP_Bot_ER_I" or defName="RPP_Bot_ER_II" or defName="RPP_Bot_ER_III" or defName="RPP_Bot_ER_IV" or defName="RPP_Bot_ER_V"]/race/mechWorkTypePriorities</xpath>
        <value>
          <MJobs_Caring>1</MJobs_Caring>
        </value>
      </li>

      <li Class="PatchOperationAdd">
        <xpath>/Defs/ThingDef[defName="RPP_Bot_Omni_I" or defName="RPP_Bot_Omni_II" or defName="RPP_Bot_Omni_III" or defName="RPP_Bot_Omni_IV" or defName="RPP_Bot_Omni_V"]/robotWorkTypes</xpath>
        <value>
          <li>
            <workTypeDef>MJobs_Caring</workTypeDef>
            <priority>1</priority>
          </li>
        </value>
      </li>

      <li Class="PatchOperationAdd">
        <xpath>/Defs/ThingDef[defName="RPP_Bot_Omni_I" or defName="RPP_Bot_Omni_II" or defName="RPP_Bot_Omni_III" or defName="RPP_Bot_Omni_IV" or defName="RPP_Bot_Omni_V"]/race/mechEnabledWorkTypes</xpath>
        <value>
          <li>MJobs_Caring</li>
        </value>
      </li>

      <li Class="PatchOperationAdd">
        <xpath>/Defs/ThingDef[defName="RPP_Bot_Omni_I" or defName="RPP_Bot_Omni_II" or defName="RPP_Bot_Omni_III" or defName="RPP_Bot_Omni_IV" or defName="RPP_Bot_Omni_V"]/race/mechWorkTypePriorities</xpath>
        <value>
          <MJobs_Caring>1</MJobs_Caring>
        </value>
      </li>

    </operations>
  </Operation>

  <!-- #endregion -->

  <!-- #region MJobs_PriorityHauling -->

  <Operation Class="ManyJobs.PatchOps.IfWorkTypeIsEnabled">
    <workType>MJobs_PriorityHauling</workType>
    <operations>

      <li Class="PatchOperationAdd">
        <xpath>/Defs/ThingDef[defName="AIRobot_Hauler" or defName="AIRobot_Hauler_II" or defName="AIRobot_Hauler_III" or defName="AIRobot_Hauler_IV" or defName="AIRobot_Hauler_V"]/robotWorkTypes</xpath>
        <value>
          <li>
            <workTypeDef>MJobs_PriorityHauling</workTypeDef>
            <priority>1</priority>
          </li>
        </value>
      </li>

      <li Class="PatchOperationAdd">
        <xpath>/Defs/ThingDef[defName="AIRobot_Hauler" or defName="AIRobot_Hauler_II" or defName="AIRobot_Hauler_III" or defName="AIRobot_Hauler_IV" or defName="AIRobot_Hauler_V"]/race/mechEnabledWorkTypes</xpath>
        <value>
          <li>MJobs_PriorityHauling</li>
        </value>
      </li>

      <li Class="PatchOperationAdd">
        <xpath>/Defs/ThingDef[defName="AIRobot_Hauler" or defName="AIRobot_Hauler_II" or defName="AIRobot_Hauler_III" or defName="AIRobot_Hauler_IV" or defName="AIRobot_Hauler_V"]/race/mechWorkTypePriorities</xpath>
        <value>
          <MJobs_PriorityHauling>1</MJobs_PriorityHauling>
        </value>
      </li>

      <li Class="PatchOperationAdd">
        <xpath>/Defs/ThingDef[defName="RPP_Bot_Omni_I" or defName="RPP_Bot_Omni_II" or defName="RPP_Bot_Omni_III" or defName="RPP_Bot_Omni_IV" or defName="RPP_Bot_Omni_V"]/robotWorkTypes</xpath>
        <value>
          <li>
            <workTypeDef>MJobs_PriorityHauling</workTypeDef>
            <priority>1</priority>
          </li>
        </value>
      </li>

      <li Class="PatchOperationAdd">
        <xpath>/Defs/ThingDef[defName="RPP_Bot_Omni_I" or defName="RPP_Bot_Omni_II" or defName="RPP_Bot_Omni_III" or defName="RPP_Bot_Omni_IV" or defName="RPP_Bot_Omni_V"]/race/mechEnabledWorkTypes</xpath>
        <value>
          <li>MJobs_PriorityHauling</li>
        </value>
      </li>

      <li Class="PatchOperationAdd">
        <xpath>/Defs/ThingDef[defName="RPP_Bot_Omni_I" or defName="RPP_Bot_Omni_II" or defName="RPP_Bot_Omni_III" or defName="RPP_Bot_Omni_IV" or defName="RPP_Bot_Omni_V"]/race/mechWorkTypePriorities</xpath>
        <value>
          <MJobs_PriorityHauling>1</MJobs_PriorityHauling>
        </value>
      </li>

    </operations>
  </Operation>

  <!-- #endregion -->

  <!-- #region MJobs_PriorityCleaning -->

  <Operation Class="ManyJobs.PatchOps.IfWorkTypeIsEnabled">
    <workType>MJobs_PriorityCleaning</workType>
    <operations>

      <li Class="PatchOperationAdd">
        <xpath>/Defs/ThingDef[defName="AIRobot_Cleaner" or defName="AIRobot_Cleaner_II" or defName="AIRobot_Cleaner_III" or defName="AIRobot_Cleaner_IV" or defName="AIRobot_Cleaner_V"]/robotWorkTypes</xpath>
        <value>
          <li>
            <workTypeDef>MJobs_PriorityCleaning</workTypeDef>
            <priority>1</priority>
          </li>
        </value>
      </li>

      <li Class="PatchOperationAdd">
        <xpath>/Defs/ThingDef[defName="AIRobot_Cleaner" or defName="AIRobot_Cleaner_II" or defName="AIRobot_Cleaner_III" or defName="AIRobot_Cleaner_IV" or defName="AIRobot_Cleaner_V"]/race/mechEnabledWorkTypes</xpath>
        <value>
          <li>MJobs_PriorityCleaning</li>
        </value>
      </li>

      <li Class="PatchOperationAdd">
        <xpath>/Defs/ThingDef[defName="AIRobot_Cleaner" or defName="AIRobot_Cleaner_II" or defName="AIRobot_Cleaner_III" or defName="AIRobot_Cleaner_IV" or defName="AIRobot_Cleaner_V"]/race/mechWorkTypePriorities</xpath>
        <value>
          <MJobs_PriorityCleaning>1</MJobs_PriorityCleaning>
        </value>
      </li>

      <li Class="PatchOperationAdd">
        <xpath>/Defs/ThingDef[defName="RPP_Bot_Omni_I" or defName="RPP_Bot_Omni_II" or defName="RPP_Bot_Omni_III" or defName="RPP_Bot_Omni_IV" or defName="RPP_Bot_Omni_V"]/robotWorkTypes</xpath>
        <value>
          <li>
            <workTypeDef>MJobs_PriorityCleaning</workTypeDef>
            <priority>1</priority>
          </li>
        </value>
      </li>

      <li Class="PatchOperationAdd">
        <xpath>/Defs/ThingDef[defName="RPP_Bot_Omni_I" or defName="RPP_Bot_Omni_II" or defName="RPP_Bot_Omni_III" or defName="RPP_Bot_Omni_IV" or defName="RPP_Bot_Omni_V"]/race/mechEnabledWorkTypes</xpath>
        <value>
          <li>MJobs_PriorityCleaning</li>
        </value>
      </li>

      <li Class="PatchOperationAdd">
        <xpath>/Defs/ThingDef[defName="RPP_Bot_Omni_I" or defName="RPP_Bot_Omni_II" or defName="RPP_Bot_Omni_III" or defName="RPP_Bot_Omni_IV" or defName="RPP_Bot_Omni_V"]/race/mechWorkTypePriorities</xpath>
        <value>
          <MJobs_PriorityCleaning>1</MJobs_PriorityCleaning>
        </value>
      </li>

    </operations>
  </Operation>

  <!-- #endregion -->

  <!-- #region MJobs_CleaningPollution -->

  <Operation Class="ManyJobs.PatchOps.IfWorkTypeIsEnabled">
    <workType>MJobs_CleaningPollution</workType>
    <operations>

      <li Class="PatchOperationAdd">
        <xpath>/Defs/ThingDef[defName="AIRobot_Cleaner" or defName="AIRobot_Cleaner_II" or defName="AIRobot_Cleaner_III" or defName="AIRobot_Cleaner_IV" or defName="AIRobot_Cleaner_V"]/robotWorkTypes</xpath>
        <value>
          <li>
            <workTypeDef>MJobs_CleaningPollution</workTypeDef>
            <priority>1</priority>
          </li>
        </value>
      </li>

      <li Class="PatchOperationAdd">
        <xpath>/Defs/ThingDef[defName="AIRobot_Cleaner" or defName="AIRobot_Cleaner_II" or defName="AIRobot_Cleaner_III" or defName="AIRobot_Cleaner_IV" or defName="AIRobot_Cleaner_V"]/race/mechEnabledWorkTypes</xpath>
        <value>
          <li>MJobs_CleaningPollution</li>
        </value>
      </li>

      <li Class="PatchOperationAdd">
        <xpath>/Defs/ThingDef[defName="AIRobot_Cleaner" or defName="AIRobot_Cleaner_II" or defName="AIRobot_Cleaner_III" or defName="AIRobot_Cleaner_IV" or defName="AIRobot_Cleaner_V"]/race/mechWorkTypePriorities</xpath>
        <value>
          <MJobs_CleaningPollution>1</MJobs_CleaningPollution>
        </value>
      </li>

      <li Class="PatchOperationAdd">
        <xpath>/Defs/ThingDef[defName="RPP_Bot_Omni_I" or defName="RPP_Bot_Omni_II" or defName="RPP_Bot_Omni_III" or defName="RPP_Bot_Omni_IV" or defName="RPP_Bot_Omni_V"]/robotWorkTypes</xpath>
        <value>
          <li>
            <workTypeDef>MJobs_CleaningPollution</workTypeDef>
            <priority>1</priority>
          </li>
        </value>
      </li>

      <li Class="PatchOperationAdd">
        <xpath>/Defs/ThingDef[defName="RPP_Bot_Omni_I" or defName="RPP_Bot_Omni_II" or defName="RPP_Bot_Omni_III" or defName="RPP_Bot_Omni_IV" or defName="RPP_Bot_Omni_V"]/race/mechEnabledWorkTypes</xpath>
        <value>
          <li>MJobs_CleaningPollution</li>
        </value>
      </li>

      <li Class="PatchOperationAdd">
        <xpath>/Defs/ThingDef[defName="RPP_Bot_Omni_I" or defName="RPP_Bot_Omni_II" or defName="RPP_Bot_Omni_III" or defName="RPP_Bot_Omni_IV" or defName="RPP_Bot_Omni_V"]/race/mechWorkTypePriorities</xpath>
        <value>
          <MJobs_CleaningPollution>1</MJobs_CleaningPollution>
        </value>
      </li>

    </operations>
  </Operation>

  <!-- #endregion -->

  <!-- #region MJobs_Undertaking -->

  <Operation Class="ManyJobs.PatchOps.IfWorkTypeIsEnabled">
    <workType>MJobs_Undertaking</workType>
    <operations>

      <li Class="PatchOperationAdd">
        <xpath>/Defs/ThingDef[defName="AIRobot_Hauler" or defName="AIRobot_Hauler_II" or defName="AIRobot_Hauler_III" or defName="AIRobot_Hauler_IV" or defName="AIRobot_Hauler_V"]/robotWorkTypes</xpath>
        <value>
          <li>
            <workTypeDef>MJobs_Undertaking</workTypeDef>
            <priority>1</priority>
          </li>
        </value>
      </li>

      <li Class="PatchOperationAdd">
        <xpath>/Defs/ThingDef[defName="AIRobot_Hauler" or defName="AIRobot_Hauler_II" or defName="AIRobot_Hauler_III" or defName="AIRobot_Hauler_IV" or defName="AIRobot_Hauler_V"]/race/mechEnabledWorkTypes</xpath>
        <value>
          <li>MJobs_Undertaking</li>
        </value>
      </li>

      <li Class="PatchOperationAdd">
        <xpath>/Defs/ThingDef[defName="AIRobot_Hauler" or defName="AIRobot_Hauler_II" or defName="AIRobot_Hauler_III" or defName="AIRobot_Hauler_IV" or defName="AIRobot_Hauler_V"]/race/mechWorkTypePriorities</xpath>
        <value>
          <MJobs_Undertaking>1</MJobs_Undertaking>
        </value>
      </li>

      <li Class="PatchOperationAdd">
        <xpath>/Defs/ThingDef[defName="RPP_Bot_Omni_I" or defName="RPP_Bot_Omni_II" or defName="RPP_Bot_Omni_III" or defName="RPP_Bot_Omni_IV" or defName="RPP_Bot_Omni_V"]/robotWorkTypes</xpath>
        <value>
          <li>
            <workTypeDef>MJobs_Undertaking</workTypeDef>
            <priority>1</priority>
          </li>
        </value>
      </li>

      <li Class="PatchOperationAdd">
        <xpath>/Defs/ThingDef[defName="RPP_Bot_Omni_I" or defName="RPP_Bot_Omni_II" or defName="RPP_Bot_Omni_III" or defName="RPP_Bot_Omni_IV" or defName="RPP_Bot_Omni_V"]/race/mechEnabledWorkTypes</xpath>
        <value>
          <li>MJobs_Undertaking</li>
        </value>
      </li>

      <li Class="PatchOperationAdd">
        <xpath>/Defs/ThingDef[defName="RPP_Bot_Omni_I" or defName="RPP_Bot_Omni_II" or defName="RPP_Bot_Omni_III" or defName="RPP_Bot_Omni_IV" or defName="RPP_Bot_Omni_V"]/race/mechWorkTypePriorities</xpath>
        <value>
          <MJobs_Undertaking>1</MJobs_Undertaking>
        </value>
      </li>

    </operations>
  </Operation>

  <!-- #endregion -->

  <!-- #region MJobs_Butchering -->

  <Operation Class="ManyJobs.PatchOps.IfWorkTypeIsEnabled">
    <workType>MJobs_Butchering</workType>
    <operations>

      <li Class="PatchOperationAdd">
        <xpath>/Defs/ThingDef[defName="RPP_Bot_Kitchen_I" or defName="RPP_Bot_Kitchen_II" or defName="RPP_Bot_Kitchen_III" or defName="RPP_Bot_Kitchen_IV" or defName="RPP_Bot_Kitchen_V"]/robotWorkTypes</xpath>
        <value>
          <li>
            <workTypeDef>MJobs_Butchering</workTypeDef>
            <priority>1</priority>
          </li>
        </value>
      </li>

      <li Class="PatchOperationAdd">
        <xpath>/Defs/ThingDef[defName="RPP_Bot_Kitchen_I" or defName="RPP_Bot_Kitchen_II" or defName="RPP_Bot_Kitchen_III" or defName="RPP_Bot_Kitchen_IV" or defName="RPP_Bot_Kitchen_V"]/race/mechEnabledWorkTypes</xpath>
        <value>
          <li>MJobs_Butchering</li>
        </value>
      </li>

      <li Class="PatchOperationAdd">
        <xpath>/Defs/ThingDef[defName="RPP_Bot_Kitchen_I" or defName="RPP_Bot_Kitchen_II" or defName="RPP_Bot_Kitchen_III" or defName="RPP_Bot_Kitchen_IV" or defName="RPP_Bot_Kitchen_V"]/race/mechWorkTypePriorities</xpath>
        <value>
          <MJobs_Butchering>1</MJobs_Butchering>
        </value>
      </li>

      <li Class="PatchOperationAdd">
        <xpath>/Defs/ThingDef[defName="RPP_Bot_Omni_I" or defName="RPP_Bot_Omni_II" or defName="RPP_Bot_Omni_III" or defName="RPP_Bot_Omni_IV" or defName="RPP_Bot_Omni_V"]/robotWorkTypes</xpath>
        <value>
          <li>
            <workTypeDef>MJobs_Butchering</workTypeDef>
            <priority>1</priority>
          </li>
        </value>
      </li>

      <li Class="PatchOperationAdd">
        <xpath>/Defs/ThingDef[defName="RPP_Bot_Omni_I" or defName="RPP_Bot_Omni_II" or defName="RPP_Bot_Omni_III" or defName="RPP_Bot_Omni_IV" or defName="RPP_Bot_Omni_V"]/race/mechEnabledWorkTypes</xpath>
        <value>
          <li>MJobs_Butchering</li>
        </value>
      </li>

      <li Class="PatchOperationAdd">
        <xpath>/Defs/ThingDef[defName="RPP_Bot_Omni_I" or defName="RPP_Bot_Omni_II" or defName="RPP_Bot_Omni_III" or defName="RPP_Bot_Omni_IV" or defName="RPP_Bot_Omni_V"]/race/mechWorkTypePriorities</xpath>
        <value>
          <MJobs_Butchering>1</MJobs_Butchering>
        </value>
      </li>

    </operations>
  </Operation>

  <!-- #endregion -->

  <!-- #region MJobs_Brewing -->

  <Operation Class="ManyJobs.PatchOps.IfWorkTypeIsEnabled">
    <workType>MJobs_Brewing</workType>
    <operations>

      <li Class="PatchOperationAdd">
        <xpath>/Defs/ThingDef[defName="RPP_Bot_Kitchen_I" or defName="RPP_Bot_Kitchen_II" or defName="RPP_Bot_Kitchen_III" or defName="RPP_Bot_Kitchen_IV" or defName="RPP_Bot_Kitchen_V"]/robotWorkTypes</xpath>
        <value>
          <li>
            <workTypeDef>MJobs_Brewing</workTypeDef>
            <priority>1</priority>
          </li>
        </value>
      </li>

      <li Class="PatchOperationAdd">
        <xpath>/Defs/ThingDef[defName="RPP_Bot_Kitchen_I" or defName="RPP_Bot_Kitchen_II" or defName="RPP_Bot_Kitchen_III" or defName="RPP_Bot_Kitchen_IV" or defName="RPP_Bot_Kitchen_V"]/race/mechEnabledWorkTypes</xpath>
        <value>
          <li>MJobs_Brewing</li>
        </value>
      </li>

      <li Class="PatchOperationAdd">
        <xpath>/Defs/ThingDef[defName="RPP_Bot_Kitchen_I" or defName="RPP_Bot_Kitchen_II" or defName="RPP_Bot_Kitchen_III" or defName="RPP_Bot_Kitchen_IV" or defName="RPP_Bot_Kitchen_V"]/race/mechWorkTypePriorities</xpath>
        <value>
          <MJobs_Brewing>1</MJobs_Brewing>
        </value>
      </li>

      <li Class="PatchOperationAdd">
        <xpath>/Defs/ThingDef[defName="RPP_Bot_Omni_I" or defName="RPP_Bot_Omni_II" or defName="RPP_Bot_Omni_III" or defName="RPP_Bot_Omni_IV" or defName="RPP_Bot_Omni_V"]/robotWorkTypes</xpath>
        <value>
          <li>
            <workTypeDef>MJobs_Brewing</workTypeDef>
            <priority>1</priority>
          </li>
        </value>
      </li>

      <li Class="PatchOperationAdd">
        <xpath>/Defs/ThingDef[defName="RPP_Bot_Omni_I" or defName="RPP_Bot_Omni_II" or defName="RPP_Bot_Omni_III" or defName="RPP_Bot_Omni_IV" or defName="RPP_Bot_Omni_V"]/race/mechEnabledWorkTypes</xpath>
        <value>
          <li>MJobs_Brewing</li>
        </value>
      </li>

      <li Class="PatchOperationAdd">
        <xpath>/Defs/ThingDef[defName="RPP_Bot_Omni_I" or defName="RPP_Bot_Omni_II" or defName="RPP_Bot_Omni_III" or defName="RPP_Bot_Omni_IV" or defName="RPP_Bot_Omni_V"]/race/mechWorkTypePriorities</xpath>
        <value>
          <MJobs_Brewing>1</MJobs_Brewing>
        </value>
      </li>

    </operations>
  </Operation>

  <!-- #endregion -->

  <!-- #region MJobs_Maintaining -->

  <Operation Class="ManyJobs.PatchOps.IfWorkTypeIsEnabled">
    <workType>MJobs_Maintaining</workType>
    <operations>

      <li Class="PatchOperationAdd">
        <xpath>/Defs/ThingDef[defName="RPP_Bot_Builder_I" or defName="RPP_Bot_Builder_II" or defName="RPP_Bot_Builder_III" or defName="RPP_Bot_Builder_IV" or defName="RPP_Bot_Builder_V"]/robotWorkTypes</xpath>
        <value>
          <li>
            <workTypeDef>MJobs_Maintaining</workTypeDef>
            <priority>1</priority>
          </li>
        </value>
      </li>

      <li Class="PatchOperationAdd">
        <xpath>/Defs/ThingDef[defName="RPP_Bot_Builder_I" or defName="RPP_Bot_Builder_II" or defName="RPP_Bot_Builder_III" or defName="RPP_Bot_Builder_IV" or defName="RPP_Bot_Builder_V"]/race/mechEnabledWorkTypes</xpath>
        <value>
          <li>MJobs_Maintaining</li>
        </value>
      </li>

      <li Class="PatchOperationAdd">
        <xpath>/Defs/ThingDef[defName="RPP_Bot_Builder_I" or defName="RPP_Bot_Builder_II" or defName="RPP_Bot_Builder_III" or defName="RPP_Bot_Builder_IV" or defName="RPP_Bot_Builder_V"]/race/mechWorkTypePriorities</xpath>
        <value>
          <MJobs_Maintaining>1</MJobs_Maintaining>
        </value>
      </li>

      <li Class="PatchOperationAdd">
        <xpath>/Defs/ThingDef[defName="RPP_Bot_Omni_I" or defName="RPP_Bot_Omni_II" or defName="RPP_Bot_Omni_III" or defName="RPP_Bot_Omni_IV" or defName="RPP_Bot_Omni_V"]/robotWorkTypes</xpath>
        <value>
          <li>
            <workTypeDef>MJobs_Maintaining</workTypeDef>
            <priority>1</priority>
          </li>
        </value>
      </li>

      <li Class="PatchOperationAdd">
        <xpath>/Defs/ThingDef[defName="RPP_Bot_Omni_I" or defName="RPP_Bot_Omni_II" or defName="RPP_Bot_Omni_III" or defName="RPP_Bot_Omni_IV" or defName="RPP_Bot_Omni_V"]/race/mechEnabledWorkTypes</xpath>
        <value>
          <li>MJobs_Maintaining</li>
        </value>
      </li>

      <li Class="PatchOperationAdd">
        <xpath>/Defs/ThingDef[defName="RPP_Bot_Omni_I" or defName="RPP_Bot_Omni_II" or defName="RPP_Bot_Omni_III" or defName="RPP_Bot_Omni_IV" or defName="RPP_Bot_Omni_V"]/race/mechWorkTypePriorities</xpath>
        <value>
          <MJobs_Maintaining>1</MJobs_Maintaining>
        </value>
      </li>

    </operations>
  </Operation>

  <!-- #endregion -->

  <!-- #region MJobs_Deconstructing -->

  <Operation Class="ManyJobs.PatchOps.IfWorkTypeIsEnabled">
    <workType>MJobs_Deconstructing</workType>
    <operations>

      <li Class="PatchOperationAdd">
        <xpath>/Defs/ThingDef[defName="RPP_Bot_Builder_I" or defName="RPP_Bot_Builder_II" or defName="RPP_Bot_Builder_III" or defName="RPP_Bot_Builder_IV" or defName="RPP_Bot_Builder_V"]/robotWorkTypes</xpath>
        <value>
          <li>
            <workTypeDef>MJobs_Deconstructing</workTypeDef>
            <priority>1</priority>
          </li>
        </value>
      </li>

      <li Class="PatchOperationAdd">
        <xpath>/Defs/ThingDef[defName="RPP_Bot_Builder_I" or defName="RPP_Bot_Builder_II" or defName="RPP_Bot_Builder_III" or defName="RPP_Bot_Builder_IV" or defName="RPP_Bot_Builder_V"]/race/mechEnabledWorkTypes</xpath>
        <value>
          <li>MJobs_Deconstructing</li>
        </value>
      </li>

      <li Class="PatchOperationAdd">
        <xpath>/Defs/ThingDef[defName="RPP_Bot_Builder_I" or defName="RPP_Bot_Builder_II" or defName="RPP_Bot_Builder_III" or defName="RPP_Bot_Builder_IV" or defName="RPP_Bot_Builder_V"]/race/mechWorkTypePriorities</xpath>
        <value>
          <MJobs_Deconstructing>1</MJobs_Deconstructing>
        </value>
      </li>

      <li Class="PatchOperationAdd">
        <xpath>/Defs/ThingDef[defName="RPP_Bot_Omni_I" or defName="RPP_Bot_Omni_II" or defName="RPP_Bot_Omni_III" or defName="RPP_Bot_Omni_IV" or defName="RPP_Bot_Omni_V"]/robotWorkTypes</xpath>
        <value>
          <li>
            <workTypeDef>MJobs_Deconstructing</workTypeDef>
            <priority>1</priority>
          </li>
        </value>
      </li>

      <li Class="PatchOperationAdd">
        <xpath>/Defs/ThingDef[defName="RPP_Bot_Omni_I" or defName="RPP_Bot_Omni_II" or defName="RPP_Bot_Omni_III" or defName="RPP_Bot_Omni_IV" or defName="RPP_Bot_Omni_V"]/race/mechEnabledWorkTypes</xpath>
        <value>
          <li>MJobs_Deconstructing</li>
        </value>
      </li>

      <li Class="PatchOperationAdd">
        <xpath>/Defs/ThingDef[defName="RPP_Bot_Omni_I" or defName="RPP_Bot_Omni_II" or defName="RPP_Bot_Omni_III" or defName="RPP_Bot_Omni_IV" or defName="RPP_Bot_Omni_V"]/race/mechWorkTypePriorities</xpath>
        <value>
          <MJobs_Deconstructing>1</MJobs_Deconstructing>
        </value>
      </li>

    </operations>
  </Operation>

  <!-- #endregion -->

  <!-- #region MJobs_Smoothing -->

  <Operation Class="ManyJobs.PatchOps.IfWorkTypeIsEnabled">
    <workType>MJobs_Smoothing</workType>
    <operations>

      <li Class="PatchOperationAdd">
        <xpath>/Defs/ThingDef[defName="RPP_Bot_Builder_I" or defName="RPP_Bot_Builder_II" or defName="RPP_Bot_Builder_III" or defName="RPP_Bot_Builder_IV" or defName="RPP_Bot_Builder_V"]/robotWorkTypes</xpath>
        <value>
          <li>
            <workTypeDef>MJobs_Smoothing</workTypeDef>
            <priority>1</priority>
          </li>
        </value>
      </li>

      <li Class="PatchOperationAdd">
        <xpath>/Defs/ThingDef[defName="RPP_Bot_Builder_I" or defName="RPP_Bot_Builder_II" or defName="RPP_Bot_Builder_III" or defName="RPP_Bot_Builder_IV" or defName="RPP_Bot_Builder_V"]/race/mechEnabledWorkTypes</xpath>
        <value>
          <li>MJobs_Smoothing</li>
        </value>
      </li>

      <li Class="PatchOperationAdd">
        <xpath>/Defs/ThingDef[defName="RPP_Bot_Builder_I" or defName="RPP_Bot_Builder_II" or defName="RPP_Bot_Builder_III" or defName="RPP_Bot_Builder_IV" or defName="RPP_Bot_Builder_V"]/race/mechWorkTypePriorities</xpath>
        <value>
          <MJobs_Smoothing>1</MJobs_Smoothing>
        </value>
      </li>

      <li Class="PatchOperationAdd">
        <xpath>/Defs/ThingDef[defName="RPP_Bot_Omni_I" or defName="RPP_Bot_Omni_II" or defName="RPP_Bot_Omni_III" or defName="RPP_Bot_Omni_IV" or defName="RPP_Bot_Omni_V"]/robotWorkTypes</xpath>
        <value>
          <li>
            <workTypeDef>MJobs_Smoothing</workTypeDef>
            <priority>1</priority>
          </li>
        </value>
      </li>

      <li Class="PatchOperationAdd">
        <xpath>/Defs/ThingDef[defName="RPP_Bot_Omni_I" or defName="RPP_Bot_Omni_II" or defName="RPP_Bot_Omni_III" or defName="RPP_Bot_Omni_IV" or defName="RPP_Bot_Omni_V"]/race/mechEnabledWorkTypes</xpath>
        <value>
          <li>MJobs_Smoothing</li>
        </value>
      </li>

      <li Class="PatchOperationAdd">
        <xpath>/Defs/ThingDef[defName="RPP_Bot_Omni_I" or defName="RPP_Bot_Omni_II" or defName="RPP_Bot_Omni_III" or defName="RPP_Bot_Omni_IV" or defName="RPP_Bot_Omni_V"]/race/mechWorkTypePriorities</xpath>
        <value>
          <MJobs_Smoothing>1</MJobs_Smoothing>
        </value>
      </li>

    </operations>
  </Operation>

  <!-- #endregion -->

  <!-- #region MJobs_Painting -->

  <Operation Class="ManyJobs.PatchOps.IfWorkTypeIsEnabled">
    <workType>MJobs_Painting</workType>
    <operations>

      <li Class="PatchOperationAdd">
        <xpath>/Defs/ThingDef[defName="RPP_Bot_Builder_I" or defName="RPP_Bot_Builder_II" or defName="RPP_Bot_Builder_III" or defName="RPP_Bot_Builder_IV" or defName="RPP_Bot_Builder_V"]/robotWorkTypes</xpath>
        <value>
          <li>
            <workTypeDef>MJobs_Painting</workTypeDef>
            <priority>1</priority>
          </li>
        </value>
      </li>

      <li Class="PatchOperationAdd">
        <xpath>/Defs/ThingDef[defName="RPP_Bot_Builder_I" or defName="RPP_Bot_Builder_II" or defName="RPP_Bot_Builder_III" or defName="RPP_Bot_Builder_IV" or defName="RPP_Bot_Builder_V"]/race/mechEnabledWorkTypes</xpath>
        <value>
          <li>MJobs_Painting</li>
        </value>
      </li>

      <li Class="PatchOperationAdd">
        <xpath>/Defs/ThingDef[defName="RPP_Bot_Builder_I" or defName="RPP_Bot_Builder_II" or defName="RPP_Bot_Builder_III" or defName="RPP_Bot_Builder_IV" or defName="RPP_Bot_Builder_V"]/race/mechWorkTypePriorities</xpath>
        <value>
          <MJobs_Painting>1</MJobs_Painting>
        </value>
      </li>

      <li Class="PatchOperationAdd">
        <xpath>/Defs/ThingDef[defName="RPP_Bot_Omni_I" or defName="RPP_Bot_Omni_II" or defName="RPP_Bot_Omni_III" or defName="RPP_Bot_Omni_IV" or defName="RPP_Bot_Omni_V"]/robotWorkTypes</xpath>
        <value>
          <li>
            <workTypeDef>MJobs_Painting</workTypeDef>
            <priority>1</priority>
          </li>
        </value>
      </li>

      <li Class="PatchOperationAdd">
        <xpath>/Defs/ThingDef[defName="RPP_Bot_Omni_I" or defName="RPP_Bot_Omni_II" or defName="RPP_Bot_Omni_III" or defName="RPP_Bot_Omni_IV" or defName="RPP_Bot_Omni_V"]/race/mechEnabledWorkTypes</xpath>
        <value>
          <li>MJobs_Painting</li>
        </value>
      </li>

      <li Class="PatchOperationAdd">
        <xpath>/Defs/ThingDef[defName="RPP_Bot_Omni_I" or defName="RPP_Bot_Omni_II" or defName="RPP_Bot_Omni_III" or defName="RPP_Bot_Omni_IV" or defName="RPP_Bot_Omni_V"]/race/mechWorkTypePriorities</xpath>
        <value>
          <MJobs_Painting>1</MJobs_Painting>
        </value>
      </li>

    </operations>
  </Operation>

  <!-- #endregion -->

  <!-- #region MJobs_Harvesting -->

  <Operation Class="ManyJobs.PatchOps.IfWorkTypeIsEnabled">
    <workType>MJobs_Harvesting</workType>
    <operations>

      <li Class="PatchOperationAdd">
        <xpath>/Defs/ThingDef[defName="RPP_Bot_Kitchen_I" or defName="RPP_Bot_Kitchen_II" or defName="RPP_Bot_Kitchen_III" or defName="RPP_Bot_Kitchen_IV" or defName="RPP_Bot_Kitchen_V"]/robotWorkTypes</xpath>
        <value>
          <li>
            <workTypeDef>MJobs_Harvesting</workTypeDef>
            <priority>1</priority>
          </li>
        </value>
      </li>

      <li Class="PatchOperationAdd">
        <xpath>/Defs/ThingDef[defName="RPP_Bot_Kitchen_I" or defName="RPP_Bot_Kitchen_II" or defName="RPP_Bot_Kitchen_III" or defName="RPP_Bot_Kitchen_IV" or defName="RPP_Bot_Kitchen_V"]/race/mechEnabledWorkTypes</xpath>
        <value>
          <li>MJobs_Harvesting</li>
        </value>
      </li>

      <li Class="PatchOperationAdd">
        <xpath>/Defs/ThingDef[defName="RPP_Bot_Kitchen_I" or defName="RPP_Bot_Kitchen_II" or defName="RPP_Bot_Kitchen_III" or defName="RPP_Bot_Kitchen_IV" or defName="RPP_Bot_Kitchen_V"]/race/mechWorkTypePriorities</xpath>
        <value>
          <MJobs_Harvesting>1</MJobs_Harvesting>
        </value>
      </li>

      <li Class="PatchOperationAdd">
        <xpath>/Defs/ThingDef[defName="RPP_Bot_Omni_I" or defName="RPP_Bot_Omni_II" or defName="RPP_Bot_Omni_III" or defName="RPP_Bot_Omni_IV" or defName="RPP_Bot_Omni_V"]/robotWorkTypes</xpath>
        <value>
          <li>
            <workTypeDef>MJobs_Harvesting</workTypeDef>
            <priority>1</priority>
          </li>
        </value>
      </li>

      <li Class="PatchOperationAdd">
        <xpath>/Defs/ThingDef[defName="RPP_Bot_Omni_I" or defName="RPP_Bot_Omni_II" or defName="RPP_Bot_Omni_III" or defName="RPP_Bot_Omni_IV" or defName="RPP_Bot_Omni_V"]/race/mechEnabledWorkTypes</xpath>
        <value>
          <li>MJobs_Harvesting</li>
        </value>
      </li>

      <li Class="PatchOperationAdd">
        <xpath>/Defs/ThingDef[defName="RPP_Bot_Omni_I" or defName="RPP_Bot_Omni_II" or defName="RPP_Bot_Omni_III" or defName="RPP_Bot_Omni_IV" or defName="RPP_Bot_Omni_V"]/race/mechWorkTypePriorities</xpath>
        <value>
          <MJobs_Harvesting>1</MJobs_Harvesting>
        </value>
      </li>

    </operations>
  </Operation>

  <!-- #endregion -->

  <!-- #region MJobs_Drilling -->

  <Operation Class="ManyJobs.PatchOps.IfWorkTypeIsEnabled">
    <workType>MJobs_Drilling</workType>
    <operations>

      <li Class="PatchOperationAdd">
        <xpath>/Defs/ThingDef[defName="RPP_Bot_Builder_I" or defName="RPP_Bot_Builder_II" or defName="RPP_Bot_Builder_III" or defName="RPP_Bot_Builder_IV" or defName="RPP_Bot_Builder_V"]/robotWorkTypes</xpath>
        <value>
          <li>
            <workTypeDef>MJobs_Drilling</workTypeDef>
            <priority>1</priority>
          </li>
        </value>
      </li>

      <li Class="PatchOperationAdd">
        <xpath>/Defs/ThingDef[defName="RPP_Bot_Builder_I" or defName="RPP_Bot_Builder_II" or defName="RPP_Bot_Builder_III" or defName="RPP_Bot_Builder_IV" or defName="RPP_Bot_Builder_V"]/race/mechEnabledWorkTypes</xpath>
        <value>
          <li>MJobs_Drilling</li>
        </value>
      </li>

      <li Class="PatchOperationAdd">
        <xpath>/Defs/ThingDef[defName="RPP_Bot_Builder_I" or defName="RPP_Bot_Builder_II" or defName="RPP_Bot_Builder_III" or defName="RPP_Bot_Builder_IV" or defName="RPP_Bot_Builder_V"]/race/mechWorkTypePriorities</xpath>
        <value>
          <MJobs_Drilling>1</MJobs_Drilling>
        </value>
      </li>

      <li Class="PatchOperationAdd">
        <xpath>/Defs/ThingDef[defName="RPP_Bot_Omni_I" or defName="RPP_Bot_Omni_II" or defName="RPP_Bot_Omni_III" or defName="RPP_Bot_Omni_IV" or defName="RPP_Bot_Omni_V"]/robotWorkTypes</xpath>
        <value>
          <li>
            <workTypeDef>MJobs_Drilling</workTypeDef>
            <priority>1</priority>
          </li>
        </value>
      </li>

      <li Class="PatchOperationAdd">
        <xpath>/Defs/ThingDef[defName="RPP_Bot_Omni_I" or defName="RPP_Bot_Omni_II" or defName="RPP_Bot_Omni_III" or defName="RPP_Bot_Omni_IV" or defName="RPP_Bot_Omni_V"]/race/mechEnabledWorkTypes</xpath>
        <value>
          <li>MJobs_Drilling</li>
        </value>
      </li>

      <li Class="PatchOperationAdd">
        <xpath>/Defs/ThingDef[defName="RPP_Bot_Omni_I" or defName="RPP_Bot_Omni_II" or defName="RPP_Bot_Omni_III" or defName="RPP_Bot_Omni_IV" or defName="RPP_Bot_Omni_V"]/race/mechWorkTypePriorities</xpath>
        <value>
          <MJobs_Drilling>1</MJobs_Drilling>
        </value>
      </li>

    </operations>
  </Operation>

  <!-- #endregion -->

  <!-- #endregion -->

  <!-- #region MJobs_Fabricating -->

  <Operation Class="ManyJobs.PatchOps.IfWorkTypeIsEnabled">
    <workType>MJobs_Fabricating</workType>
    <operations>

      <li Class="PatchOperationAdd">
        <xpath>/Defs/ThingDef[defName="RPP_Bot_Crafter_I" or defName="RPP_Bot_Crafter_II" or defName="RPP_Bot_Crafter_III" or defName="RPP_Bot_Crafter_IV" or defName="RPP_Bot_Crafter_V"]/robotWorkTypes</xpath>
        <value>
          <li>
            <workTypeDef>MJobs_Fabricating</workTypeDef>
            <priority>1</priority>
          </li>
        </value>
      </li>

      <li Class="PatchOperationAdd">
        <xpath>/Defs/ThingDef[defName="RPP_Bot_Crafter_I" or defName="RPP_Bot_Crafter_II" or defName="RPP_Bot_Crafter_III" or defName="RPP_Bot_Crafter_IV" or defName="RPP_Bot_Crafter_V"]/race/mechEnabledWorkTypes</xpath>
        <value>
          <li>MJobs_Fabricating</li>
        </value>
      </li>

      <li Class="PatchOperationAdd">
        <xpath>/Defs/ThingDef[defName="RPP_Bot_Crafter_I" or defName="RPP_Bot_Crafter_II" or defName="RPP_Bot_Crafter_III" or defName="RPP_Bot_Crafter_IV" or defName="RPP_Bot_Crafter_V"]/race/mechWorkTypePriorities</xpath>
        <value>
          <MJobs_Fabricating>1</MJobs_Fabricating>
        </value>
      </li>

      <li Class="PatchOperationAdd">
        <xpath>/Defs/ThingDef[defName="RPP_Bot_Omni_I" or defName="RPP_Bot_Omni_II" or defName="RPP_Bot_Omni_III" or defName="RPP_Bot_Omni_IV" or defName="RPP_Bot_Omni_V"]/robotWorkTypes</xpath>
        <value>
          <li>
            <workTypeDef>MJobs_Fabricating</workTypeDef>
            <priority>1</priority>
          </li>
        </value>
      </li>

      <li Class="PatchOperationAdd">
        <xpath>/Defs/ThingDef[defName="RPP_Bot_Omni_I" or defName="RPP_Bot_Omni_II" or defName="RPP_Bot_Omni_III" or defName="RPP_Bot_Omni_IV" or defName="RPP_Bot_Omni_V"]/race/mechEnabledWorkTypes</xpath>
        <value>
          <li>MJobs_Fabricating</li>
        </value>
      </li>

      <li Class="PatchOperationAdd">
        <xpath>/Defs/ThingDef[defName="RPP_Bot_Omni_I" or defName="RPP_Bot_Omni_II" or defName="RPP_Bot_Omni_III" or defName="RPP_Bot_Omni_IV" or defName="RPP_Bot_Omni_V"]/race/mechWorkTypePriorities</xpath>
        <value>
          <MJobs_Fabricating>1</MJobs_Fabricating>
        </value>
      </li>

    </operations>
  </Operation>

  <!-- #endregion -->

  <!-- #region MJobs_Synthesizing -->

  <Operation Class="ManyJobs.PatchOps.IfWorkTypeIsEnabled">
    <workType>MJobs_Synthesizing</workType>
    <operations>

      <li Class="PatchOperationAdd">
        <xpath>/Defs/ThingDef[defName="RPP_Bot_Crafter_I" or defName="RPP_Bot_Crafter_II" or defName="RPP_Bot_Crafter_III" or defName="RPP_Bot_Crafter_IV" or defName="RPP_Bot_Crafter_V"]/robotWorkTypes</xpath>
        <value>
          <li>
            <workTypeDef>MJobs_Synthesizing</workTypeDef>
            <priority>1</priority>
          </li>
        </value>
      </li>

      <li Class="PatchOperationAdd">
        <xpath>/Defs/ThingDef[defName="RPP_Bot_Crafter_I" or defName="RPP_Bot_Crafter_II" or defName="RPP_Bot_Crafter_III" or defName="RPP_Bot_Crafter_IV" or defName="RPP_Bot_Crafter_V"]/race/mechEnabledWorkTypes</xpath>
        <value>
          <li>MJobs_Synthesizing</li>
        </value>
      </li>

      <li Class="PatchOperationAdd">
        <xpath>/Defs/ThingDef[defName="RPP_Bot_Crafter_I" or defName="RPP_Bot_Crafter_II" or defName="RPP_Bot_Crafter_III" or defName="RPP_Bot_Crafter_IV" or defName="RPP_Bot_Crafter_V"]/race/mechWorkTypePriorities</xpath>
        <value>
          <MJobs_Synthesizing>1</MJobs_Synthesizing>
        </value>
      </li>

      <li Class="PatchOperationAdd">
        <xpath>/Defs/ThingDef[defName="RPP_Bot_Omni_I" or defName="RPP_Bot_Omni_II" or defName="RPP_Bot_Omni_III" or defName="RPP_Bot_Omni_IV" or defName="RPP_Bot_Omni_V"]/robotWorkTypes</xpath>
        <value>
          <li>
            <workTypeDef>MJobs_Synthesizing</workTypeDef>
            <priority>1</priority>
          </li>
        </value>
      </li>

      <li Class="PatchOperationAdd">
        <xpath>/Defs/ThingDef[defName="RPP_Bot_Omni_I" or defName="RPP_Bot_Omni_II" or defName="RPP_Bot_Omni_III" or defName="RPP_Bot_Omni_IV" or defName="RPP_Bot_Omni_V"]/race/mechEnabledWorkTypes</xpath>
        <value>
          <li>MJobs_Synthesizing</li>
        </value>
      </li>

      <li Class="PatchOperationAdd">
        <xpath>/Defs/ThingDef[defName="RPP_Bot_Omni_I" or defName="RPP_Bot_Omni_II" or defName="RPP_Bot_Omni_III" or defName="RPP_Bot_Omni_IV" or defName="RPP_Bot_Omni_V"]/race/mechWorkTypePriorities</xpath>
        <value>
          <MJobs_Synthesizing>1</MJobs_Synthesizing>
        </value>
      </li>

    </operations>
  </Operation>

  <!-- #endregion -->

  <!-- #region MJobs_Refining -->

  <Operation Class="ManyJobs.PatchOps.IfWorkTypeIsEnabled">
    <workType>MJobs_Refining</workType>
    <operations>

      <li Class="PatchOperationAdd">
        <xpath>/Defs/ThingDef[defName="RPP_Bot_Crafter_I" or defName="RPP_Bot_Crafter_II" or defName="RPP_Bot_Crafter_III" or defName="RPP_Bot_Crafter_IV" or defName="RPP_Bot_Crafter_V"]/robotWorkTypes</xpath>
        <value>
          <li>
            <workTypeDef>MJobs_Refining</workTypeDef>
            <priority>1</priority>
          </li>
        </value>
      </li>

      <li Class="PatchOperationAdd">
        <xpath>/Defs/ThingDef[defName="RPP_Bot_Crafter_I" or defName="RPP_Bot_Crafter_II" or defName="RPP_Bot_Crafter_III" or defName="RPP_Bot_Crafter_IV" or defName="RPP_Bot_Crafter_V"]/race/mechEnabledWorkTypes</xpath>
        <value>
          <li>MJobs_Refining</li>
        </value>
      </li>

      <li Class="PatchOperationAdd">
        <xpath>/Defs/ThingDef[defName="RPP_Bot_Crafter_I" or defName="RPP_Bot_Crafter_II" or defName="RPP_Bot_Crafter_III" or defName="RPP_Bot_Crafter_IV" or defName="RPP_Bot_Crafter_V"]/race/mechWorkTypePriorities</xpath>
        <value>
          <MJobs_Refining>1</MJobs_Refining>
        </value>
      </li>

      <li Class="PatchOperationAdd">
        <xpath>/Defs/ThingDef[defName="RPP_Bot_Omni_I" or defName="RPP_Bot_Omni_II" or defName="RPP_Bot_Omni_III" or defName="RPP_Bot_Omni_IV" or defName="RPP_Bot_Omni_V"]/robotWorkTypes</xpath>
        <value>
          <li>
            <workTypeDef>MJobs_Refining</workTypeDef>
            <priority>1</priority>
          </li>
        </value>
      </li>

      <li Class="PatchOperationAdd">
        <xpath>/Defs/ThingDef[defName="RPP_Bot_Omni_I" or defName="RPP_Bot_Omni_II" or defName="RPP_Bot_Omni_III" or defName="RPP_Bot_Omni_IV" or defName="RPP_Bot_Omni_V"]/race/mechEnabledWorkTypes</xpath>
        <value>
          <li>MJobs_Refining</li>
        </value>
      </li>

      <li Class="PatchOperationAdd">
        <xpath>/Defs/ThingDef[defName="RPP_Bot_Omni_I" or defName="RPP_Bot_Omni_II" or defName="RPP_Bot_Omni_III" or defName="RPP_Bot_Omni_IV" or defName="RPP_Bot_Omni_V"]/race/mechWorkTypePriorities</xpath>
        <value>
          <MJobs_Refining>1</MJobs_Refining>
        </value>
      </li>

    </operations>
  </Operation>

  <!-- #endregion -->

  <!-- #region MJobs_Smelting -->

  <Operation Class="ManyJobs.PatchOps.IfWorkTypeIsEnabled">
    <workType>MJobs_Smelting</workType>
    <operations>

      <li Class="PatchOperationAdd">
        <xpath>/Defs/ThingDef[defName="RPP_Bot_Crafter_I" or defName="RPP_Bot_Crafter_II" or defName="RPP_Bot_Crafter_III" or defName="RPP_Bot_Crafter_IV" or defName="RPP_Bot_Crafter_V"]/robotWorkTypes</xpath>
        <value>
          <li>
            <workTypeDef>MJobs_Smelting</workTypeDef>
            <priority>1</priority>
          </li>
        </value>
      </li>

      <li Class="PatchOperationAdd">
        <xpath>/Defs/ThingDef[defName="RPP_Bot_Crafter_I" or defName="RPP_Bot_Crafter_II" or defName="RPP_Bot_Crafter_III" or defName="RPP_Bot_Crafter_IV" or defName="RPP_Bot_Crafter_V"]/race/mechEnabledWorkTypes</xpath>
        <value>
          <li>MJobs_Smelting</li>
        </value>
      </li>

      <li Class="PatchOperationAdd">
        <xpath>/Defs/ThingDef[defName="RPP_Bot_Crafter_I" or defName="RPP_Bot_Crafter_II" or defName="RPP_Bot_Crafter_III" or defName="RPP_Bot_Crafter_IV" or defName="RPP_Bot_Crafter_V"]/race/mechWorkTypePriorities</xpath>
        <value>
          <MJobs_Smelting>1</MJobs_Smelting>
        </value>
      </li>

      <li Class="PatchOperationAdd">
        <xpath>/Defs/ThingDef[defName="RPP_Bot_Omni_I" or defName="RPP_Bot_Omni_II" or defName="RPP_Bot_Omni_III" or defName="RPP_Bot_Omni_IV" or defName="RPP_Bot_Omni_V"]/robotWorkTypes</xpath>
        <value>
          <li>
            <workTypeDef>MJobs_Smelting</workTypeDef>
            <priority>1</priority>
          </li>
        </value>
      </li>

      <li Class="PatchOperationAdd">
        <xpath>/Defs/ThingDef[defName="RPP_Bot_Omni_I" or defName="RPP_Bot_Omni_II" or defName="RPP_Bot_Omni_III" or defName="RPP_Bot_Omni_IV" or defName="RPP_Bot_Omni_V"]/race/mechEnabledWorkTypes</xpath>
        <value>
          <li>MJobs_Smelting</li>
        </value>
      </li>

      <li Class="PatchOperationAdd">
        <xpath>/Defs/ThingDef[defName="RPP_Bot_Omni_I" or defName="RPP_Bot_Omni_II" or defName="RPP_Bot_Omni_III" or defName="RPP_Bot_Omni_IV" or defName="RPP_Bot_Omni_V"]/race/mechWorkTypePriorities</xpath>
        <value>
          <MJobs_Smelting>1</MJobs_Smelting>
        </value>
      </li>

    </operations>
  </Operation>

  <!-- #endregion -->

  <!-- #region MJobs_Stonecutting -->

  <Operation Class="ManyJobs.PatchOps.IfWorkTypeIsEnabled">
    <workType>MJobs_Stonecutting</workType>
    <operations>

      <li Class="PatchOperationAdd">
        <xpath>/Defs/ThingDef[defName="RPP_Bot_Omni_I" or defName="RPP_Bot_Omni_II" or defName="RPP_Bot_Omni_III" or defName="RPP_Bot_Omni_IV" or defName="RPP_Bot_Omni_V"]/robotWorkTypes</xpath>
        <value>
          <li>
            <workTypeDef>MJobs_Stonecutting</workTypeDef>
            <priority>1</priority>
          </li>
        </value>
      </li>

      <li Class="PatchOperationAdd">
        <xpath>/Defs/ThingDef[defName="RPP_Bot_Omni_I" or defName="RPP_Bot_Omni_II" or defName="RPP_Bot_Omni_III" or defName="RPP_Bot_Omni_IV" or defName="RPP_Bot_Omni_V"]/race/mechEnabledWorkTypes</xpath>
        <value>
          <li>MJobs_Stonecutting</li>
        </value>
      </li>

      <li Class="PatchOperationAdd">
        <xpath>/Defs/ThingDef[defName="RPP_Bot_Omni_I" or defName="RPP_Bot_Omni_II" or defName="RPP_Bot_Omni_III" or defName="RPP_Bot_Omni_IV" or defName="RPP_Bot_Omni_V"]/race/mechWorkTypePriorities</xpath>
        <value>
          <MJobs_Stonecutting>1</MJobs_Stonecutting>
        </value>
      </li>

    </operations>
  </Operation>

  <!-- #endregion -->

  <!-- #region MJobs_Delivering -->

  <Operation Class="ManyJobs.PatchOps.IfWorkTypeIsEnabled">
    <workType>MJobs_Delivering</workType>
    <operations>

      <li Class="PatchOperationAdd">
        <xpath>/Defs/ThingDef[defName="AIRobot_Hauler" or defName="AIRobot_Hauler_II" or defName="AIRobot_Hauler_III" or defName="AIRobot_Hauler_IV" or defName="AIRobot_Hauler_V"]/robotWorkTypes</xpath>
        <value>
          <li>
            <workTypeDef>MJobs_Delivering</workTypeDef>
            <priority>1</priority>
          </li>
        </value>
      </li>

      <li Class="PatchOperationAdd">
        <xpath>/Defs/ThingDef[defName="AIRobot_Hauler" or defName="AIRobot_Hauler_II" or defName="AIRobot_Hauler_III" or defName="AIRobot_Hauler_IV" or defName="AIRobot_Hauler_V"]/race/mechEnabledWorkTypes</xpath>
        <value>
          <li>MJobs_Delivering</li>
        </value>
      </li>

      <li Class="PatchOperationAdd">
        <xpath>/Defs/ThingDef[defName="AIRobot_Hauler" or defName="AIRobot_Hauler_II" or defName="AIRobot_Hauler_III" or defName="AIRobot_Hauler_IV" or defName="AIRobot_Hauler_V"]/race/mechWorkTypePriorities</xpath>
        <value>
          <MJobs_Delivering>1</MJobs_Delivering>
        </value>
      </li>

      <li Class="PatchOperationAdd">
        <xpath>/Defs/ThingDef[defName="RPP_Bot_Builder_I" or defName="RPP_Bot_Builder_II" or defName="RPP_Bot_Builder_III" or defName="RPP_Bot_Builder_IV" or defName="RPP_Bot_Builder_V"]/robotWorkTypes</xpath>
        <value>
          <li>
            <workTypeDef>MJobs_Delivering</workTypeDef>
            <priority>1</priority>
          </li>
        </value>
      </li>

      <li Class="PatchOperationAdd">
        <xpath>/Defs/ThingDef[defName="RPP_Bot_Builder_I" or defName="RPP_Bot_Builder_II" or defName="RPP_Bot_Builder_III" or defName="RPP_Bot_Builder_IV" or defName="RPP_Bot_Builder_V"]/race/mechEnabledWorkTypes</xpath>
        <value>
          <li>MJobs_Delivering</li>
        </value>
      </li>

      <li Class="PatchOperationAdd">
        <xpath>/Defs/ThingDef[defName="RPP_Bot_Builder_I" or defName="RPP_Bot_Builder_II" or defName="RPP_Bot_Builder_III" or defName="RPP_Bot_Builder_IV" or defName="RPP_Bot_Builder_V"]/race/mechWorkTypePriorities</xpath>
        <value>
          <MJobs_Delivering>1</MJobs_Delivering>
        </value>
      </li>

      <li Class="PatchOperationAdd">
        <xpath>/Defs/ThingDef[defName="RPP_Bot_Omni_I" or defName="RPP_Bot_Omni_II" or defName="RPP_Bot_Omni_III" or defName="RPP_Bot_Omni_IV" or defName="RPP_Bot_Omni_V"]/robotWorkTypes</xpath>
        <value>
          <li>
            <workTypeDef>MJobs_Delivering</workTypeDef>
            <priority>1</priority>
          </li>
        </value>
      </li>

      <li Class="PatchOperationAdd">
        <xpath>/Defs/ThingDef[defName="RPP_Bot_Omni_I" or defName="RPP_Bot_Omni_II" or defName="RPP_Bot_Omni_III" or defName="RPP_Bot_Omni_IV" or defName="RPP_Bot_Omni_V"]/race/mechEnabledWorkTypes</xpath>
        <value>
          <li>MJobs_Delivering</li>
        </value>
      </li>

      <li Class="PatchOperationAdd">
        <xpath>/Defs/ThingDef[defName="RPP_Bot_Omni_I" or defName="RPP_Bot_Omni_II" or defName="RPP_Bot_Omni_III" or defName="RPP_Bot_Omni_IV" or defName="RPP_Bot_Omni_V"]/race/mechWorkTypePriorities</xpath>
        <value>
          <MJobs_Delivering>1</MJobs_Delivering>
        </value>
      </li>

    </operations>
  </Operation>

  <!-- #endregion -->

  <!-- #region MJobs_Loading -->

  <Operation Class="ManyJobs.PatchOps.IfWorkTypeIsEnabled">
    <workType>MJobs_Loading</workType>
    <operations>

      <li Class="PatchOperationAdd">
        <xpath>/Defs/ThingDef[defName="AIRobot_Hauler" or defName="AIRobot_Hauler_II" or defName="AIRobot_Hauler_III" or defName="AIRobot_Hauler_IV" or defName="AIRobot_Hauler_V"]/robotWorkTypes</xpath>
        <value>
          <li>
            <workTypeDef>MJobs_Loading</workTypeDef>
            <priority>1</priority>
          </li>
        </value>
      </li>

      <li Class="PatchOperationAdd">
        <xpath>/Defs/ThingDef[defName="AIRobot_Hauler" or defName="AIRobot_Hauler_II" or defName="AIRobot_Hauler_III" or defName="AIRobot_Hauler_IV" or defName="AIRobot_Hauler_V"]/race/mechEnabledWorkTypes</xpath>
        <value>
          <li>MJobs_Loading</li>
        </value>
      </li>

      <li Class="PatchOperationAdd">
        <xpath>/Defs/ThingDef[defName="AIRobot_Hauler" or defName="AIRobot_Hauler_II" or defName="AIRobot_Hauler_III" or defName="AIRobot_Hauler_IV" or defName="AIRobot_Hauler_V"]/race/mechWorkTypePriorities</xpath>
        <value>
          <MJobs_Loading>1</MJobs_Loading>
        </value>
      </li>

      <li Class="PatchOperationAdd">
        <xpath>/Defs/ThingDef[defName="RPP_Bot_Omni_I" or defName="RPP_Bot_Omni_II" or defName="RPP_Bot_Omni_III" or defName="RPP_Bot_Omni_IV" or defName="RPP_Bot_Omni_V"]/robotWorkTypes</xpath>
        <value>
          <li>
            <workTypeDef>MJobs_Loading</workTypeDef>
            <priority>1</priority>
          </li>
        </value>
      </li>

      <li Class="PatchOperationAdd">
        <xpath>/Defs/ThingDef[defName="RPP_Bot_Omni_I" or defName="RPP_Bot_Omni_II" or defName="RPP_Bot_Omni_III" or defName="RPP_Bot_Omni_IV" or defName="RPP_Bot_Omni_V"]/race/mechEnabledWorkTypes</xpath>
        <value>
          <li>MJobs_Loading</li>
        </value>
      </li>

      <li Class="PatchOperationAdd">
        <xpath>/Defs/ThingDef[defName="RPP_Bot_Omni_I" or defName="RPP_Bot_Omni_II" or defName="RPP_Bot_Omni_III" or defName="RPP_Bot_Omni_IV" or defName="RPP_Bot_Omni_V"]/race/mechWorkTypePriorities</xpath>
        <value>
          <MJobs_Loading>1</MJobs_Loading>
        </value>
      </li>

    </operations>
  </Operation>

  <!-- #endregion -->

  <!-- #region MJobs_Merging -->

  <Operation Class="ManyJobs.PatchOps.IfWorkTypeIsEnabled">
    <workType>MJobs_Merging</workType>
    <operations>

      <li Class="PatchOperationAdd">
        <xpath>/Defs/ThingDef[defName="AIRobot_Hauler" or defName="AIRobot_Hauler_II" or defName="AIRobot_Hauler_III" or defName="AIRobot_Hauler_IV" or defName="AIRobot_Hauler_V"]/robotWorkTypes</xpath>
        <value>
          <li>
            <workTypeDef>MJobs_Merging</workTypeDef>
            <priority>1</priority>
          </li>
        </value>
      </li>

      <li Class="PatchOperationAdd">
        <xpath>/Defs/ThingDef[defName="AIRobot_Hauler" or defName="AIRobot_Hauler_II" or defName="AIRobot_Hauler_III" or defName="AIRobot_Hauler_IV" or defName="AIRobot_Hauler_V"]/race/mechEnabledWorkTypes</xpath>
        <value>
          <li>MJobs_Merging</li>
        </value>
      </li>

      <li Class="PatchOperationAdd">
        <xpath>/Defs/ThingDef[defName="AIRobot_Hauler" or defName="AIRobot_Hauler_II" or defName="AIRobot_Hauler_III" or defName="AIRobot_Hauler_IV" or defName="AIRobot_Hauler_V"]/race/mechWorkTypePriorities</xpath>
        <value>
          <MJobs_Merging>1</MJobs_Merging>
        </value>
      </li>

      <li Class="PatchOperationAdd">
        <xpath>/Defs/ThingDef[defName="RPP_Bot_Omni_I" or defName="RPP_Bot_Omni_II" or defName="RPP_Bot_Omni_III" or defName="RPP_Bot_Omni_IV" or defName="RPP_Bot_Omni_V"]/robotWorkTypes</xpath>
        <value>
          <li>
            <workTypeDef>MJobs_Merging</workTypeDef>
            <priority>1</priority>
          </li>
        </value>
      </li>

      <li Class="PatchOperationAdd">
        <xpath>/Defs/ThingDef[defName="RPP_Bot_Omni_I" or defName="RPP_Bot_Omni_II" or defName="RPP_Bot_Omni_III" or defName="RPP_Bot_Omni_IV" or defName="RPP_Bot_Omni_V"]/race/mechEnabledWorkTypes</xpath>
        <value>
          <li>MJobs_Merging</li>
        </value>
      </li>

      <li Class="PatchOperationAdd">
        <xpath>/Defs/ThingDef[defName="RPP_Bot_Omni_I" or defName="RPP_Bot_Omni_II" or defName="RPP_Bot_Omni_III" or defName="RPP_Bot_Omni_IV" or defName="RPP_Bot_Omni_V"]/race/mechWorkTypePriorities</xpath>
        <value>
          <MJobs_Merging>1</MJobs_Merging>
        </value>
      </li>

    </operations>
  </Operation>

  <!-- #endregion -->

  <!-- #region MJobs_Scanning -->

  <Operation Class="ManyJobs.PatchOps.IfWorkTypeIsEnabled">
    <workType>MJobs_Scanning</workType>
    <operations>

      <li Class="PatchOperationAdd">
        <xpath>/Defs/ThingDef[defName="RPP_Bot_Omni_I" or defName="RPP_Bot_Omni_II" or defName="RPP_Bot_Omni_III" or defName="RPP_Bot_Omni_IV" or defName="RPP_Bot_Omni_V"]/robotWorkTypes</xpath>
        <value>
          <li>
            <workTypeDef>MJobs_Scanning</workTypeDef>
            <priority>1</priority>
          </li>
        </value>
      </li>

      <li Class="PatchOperationAdd">
        <xpath>/Defs/ThingDef[defName="RPP_Bot_Omni_I" or defName="RPP_Bot_Omni_II" or defName="RPP_Bot_Omni_III" or defName="RPP_Bot_Omni_IV" or defName="RPP_Bot_Omni_V"]/race/mechEnabledWorkTypes</xpath>
        <value>
          <li>MJobs_Scanning</li>
        </value>
      </li>

      <li Class="PatchOperationAdd">
        <xpath>/Defs/ThingDef[defName="RPP_Bot_Omni_I" or defName="RPP_Bot_Omni_II" or defName="RPP_Bot_Omni_III" or defName="RPP_Bot_Omni_IV" or defName="RPP_Bot_Omni_V"]/race/mechWorkTypePriorities</xpath>
        <value>
          <MJobs_Scanning>1</MJobs_Scanning>
        </value>
      </li>

    </operations>
  </Operation>

  <!-- #endregion -->

</Patch>
